{
	"paymentSteps": [
		{
			"number": 1,
			"name": "Account",
			"status": "completed"
		},
		{
			"number": 2,
			"name": "Shipping",
			"status": "completed"
		},
		{
			"number": 3,
			"name": "Billing",
			"status": "inProgress"
		},
		{
			"number": 4,
			"name": "Review",
			"status": "none"
		}
	],
	"basketItems": [
		{
			"id": "sdf86293ye",
			"title": "Amet minim mollit non deserunt ullamco est sit",
			"image": "/assets/images/jacket@2x.png",
			"price": "525",
			"count": "1"
		},
		{
			"id": "83hsn8fg3d",
			"title": "Amet minim mollit non",
			"image": "/assets/images/boots@2x.png",
			"price": "525",
			"count": "1"
		}
	]
}
